[
    {
        "id": 1388534400000,
        "author": "Pete Hunt",
        "text": "Hey there!"
    },
    {
        "id": 1459792223121,
        "author": "Dog",
        "text": "woof woof"
    },
    {
        "id": 1460110757045,
        "author": "me",
        "text": "foo"
    },
    {
        "id": 1460110762678,
        "author": "boo",
        "text": "hoo"
    },
    {
        "id": 1461110762678,
        "author": "cow",
        "text": "bow"
    },
    {
        "id": 1460110917141,
        "author": "holy",
        "text": "moo"
    }
]